LICENSE
README.md
pyproject.toml
setup.py
src/SynackAPI.egg-info/PKG-INFO
src/SynackAPI.egg-info/SOURCES.txt
src/SynackAPI.egg-info/dependency_links.txt
src/SynackAPI.egg-info/requires.txt
src/SynackAPI.egg-info/top_level.txt
src/synack/__init__.py
src/synack/_handler.py
src/synack/_state.py
src/synack/db/__init__.py
src/synack/db/alembic.ini
src/synack/db/alembic/README
src/synack/db/alembic/__init__.py
src/synack/db/alembic/env.py
src/synack/db/alembic/script.py.mako
src/synack/db/alembic/versions/0c1ac7be711c_added_url_table_deleted_url_from_port_.py
src/synack/db/alembic/versions/349c447c0d37_added_use_scratchspace_setting.py
src/synack/db/alembic/versions/355984ba030b_added_notification_settings.py
src/synack/db/alembic/versions/649443e08834_initial.py
src/synack/db/alembic/versions/__init__.py
src/synack/db/alembic/versions/deb7dd07212c_added_ip_port_tables.py
src/synack/db/models/__init__.py
src/synack/db/models/category.py
src/synack/db/models/config.py
src/synack/db/models/ip.py
src/synack/db/models/organization.py
src/synack/db/models/port.py
src/synack/db/models/target.py
src/synack/db/models/url.py
src/synack/plugins/__init__.py
src/synack/plugins/alerts.py
src/synack/plugins/api.py
src/synack/plugins/auth.py
src/synack/plugins/base.py
src/synack/plugins/db.py
src/synack/plugins/debug.py
src/synack/plugins/hydra.py
src/synack/plugins/missions.py
src/synack/plugins/notifications.py
src/synack/plugins/scratchspace.py
src/synack/plugins/targets.py
src/synack/plugins/templates.py
src/synack/plugins/transactions.py
src/synack/plugins/users.py
test/test_alerts.py
test/test_api.py
test/test_auth.py
test/test_db.py
test/test_debug.py
test/test_handler.py
test/test_hydra.py
test/test_missions.py
test/test_notifications.py
test/test_scratchspace.py
test/test_state.py
test/test_targets.py
test/test_templates.py
test/test_transactions.py
test/test_users.py