Metadata-Version: 2.1
Name: SynackAPI
Version: 0.2.7
Summary: A package to interact with Synack's API
Home-page: https://www.github.com/bamhm182/synackAPI
Author: bamhm182
Author-email: bamhm182@gmail.com
License: UNKNOWN
Platform: UNKNOWN
Classifier: Programming Language :: Python :: 3
Classifier: License :: OSI Approved :: MIT License
Classifier: Operating System :: OS Independent
Requires-Python: >=3.6
License-File: LICENSE
